detect/__init__.py
detect/middleware.py
django_detect-1.0.20.dist-info/METADATA
django_detect-1.0.20.dist-info/WHEEL
django_detect-1.0.20.dist-info/top_level.txt
django_detect-1.0.20.dist-info/RECORD
