Metadata-Version: 2.1
Name: django-detect
Version: 1.0.20
Summary: Django UserAgent Detect
Home-page: https://github.com/Brightcells/django-detect
Author: Hackathon
Author-email: kimi.huang@brightcells.com
License: UNKNOWN
Keywords: django-detect
Platform: UNKNOWN
Classifier: Development Status :: 5 - Production/Stable
Classifier: Environment :: Web Environment
Classifier: Framework :: Django
Classifier: Intended Audience :: Developers
Classifier: Programming Language :: Python
Classifier: Topic :: Software Development :: Libraries :: Python Modules
Classifier: Topic :: Office/Business :: Financial :: Spreadsheet
Requires-Dist: django-six
